LICENSE
MANIFEST.in
README.rst
setup.py
data_migration/__init__.py
data_migration/migration.py
data_migration/models.py
data_migration/utils.py
data_migration/version.py
data_migration/management/__init__.py
data_migration/management/commands/__init__.py
data_migration/management/commands/migrate_legacy_data.py
data_migration/management/commands/migrate_this_shit.py
django_data_migration.egg-info/PKG-INFO
django_data_migration.egg-info/SOURCES.txt
django_data_migration.egg-info/dependency_links.txt
django_data_migration.egg-info/requires.txt
django_data_migration.egg-info/top_level.txt