Metadata-Version: 1.1
Name: django-data-migration
Version: 0.2.0
Summary: Data migration framework for Django that migrates legacy data into your new django app
Home-page: https://github.com/pboehm/django-data-migration
Author: Philipp Böhm
Author-email: dev@pboehm.org
License: MIT License
Platform: UNKNOWN
Classifier: Environment :: Web Environment
Classifier: Framework :: Django
Classifier: Intended Audience :: Developers
Classifier: License :: OSI Approved :: MIT License
Classifier: Operating System :: OS Independent
Classifier: Programming Language :: Python
Classifier: Programming Language :: Python :: 2
Classifier: Programming Language :: Python :: 2.7
Classifier: Programming Language :: Python :: 3
Classifier: Programming Language :: Python :: 3.3
Classifier: Topic :: Internet :: WWW/HTTP
Classifier: Topic :: Internet :: WWW/HTTP :: Dynamic Content
